ntp_facade_smr/__init__.py
ntp_facade_smr/facade.py
ntp_facade_smr-1.1.0.dist-info/licenses/LICENSE
ntp_facade_smr-1.1.0.dist-info/METADATA
ntp_facade_smr-1.1.0.dist-info/WHEEL
ntp_facade_smr-1.1.0.dist-info/top_level.txt
ntp_facade_smr-1.1.0.dist-info/RECORD
