Metadata-Version: 2.4
Name: ntp_facade_smr
Version: 1.1.0
Summary: A simple facade for NTP time synchronization.
Author-email: Cy Dixon <cydaniel@ymail.com>
Project-URL: Homepage, https://github.com/cylissama
Classifier: Programming Language :: Python :: 3
Classifier: License :: OSI Approved :: MIT License
Classifier: Operating System :: OS Independent
Classifier: Topic :: Software Development :: Libraries :: Python Modules
Classifier: Topic :: System :: Networking :: Time Synchronization
Requires-Python: >=3.7
License-File: LICENSE
Requires-Dist: ntplib
Dynamic: license-file
